dfs_tool/__init__.py
dfs_tool/api.py
dfs_tool/dfs_tool.py
dfs_tool/tools.py
dfs_tool-0.0.10.dist-info/LICENSE
dfs_tool-0.0.10.dist-info/METADATA
dfs_tool-0.0.10.dist-info/WHEEL
dfs_tool-0.0.10.dist-info/entry_points.txt
dfs_tool-0.0.10.dist-info/top_level.txt
dfs_tool-0.0.10.dist-info/RECORD
