Metadata-Version: 2.1
Name: dfs-tool
Version: 0.0.10
Summary: Hadoop HDFS cli
Home-page: https://github.com/stonezhong/dfs_tool
Author: Stone Zhong
Author-email: stonezhong@hotmail.com
License: MIT
Platform: UNKNOWN
Classifier: License :: OSI Approved :: MIT License
Classifier: Programming Language :: Python :: 2
Classifier: Programming Language :: Python :: 3
Requires-Dist: pywebhdfs
